{"chunk_definitions":[{"row":14,"row_count":1,"visible":true,"expansion_state":0,"options":{"engine":"r","echo":false,"label":"unnamed-chunk-276"},"document_id":"7980DB40","chunk_id":"cbqm0pvrvhnhd","chunk_label":"unnamed-chunk-1"},{"row":21,"row_count":1,"visible":true,"expansion_state":0,"options":{"engine":"r","echo":false,"message":false,"warning":false,"label":"unnamed-chunk-277"},"document_id":"7980DB40","chunk_id":"cr5sqw6rrorb3","chunk_label":"unnamed-chunk-2"},{"row":32,"row_count":1,"visible":true,"expansion_state":0,"options":{"engine":"r","label":"read"},"document_id":"7980DB40","chunk_id":"c37mbcebstetk","chunk_label":"read"},{"row":53,"row_count":1,"visible":true,"expansion_state":0,"options":{"engine":"r","label":"unnamed-chunk-278"},"document_id":"7980DB40","chunk_id":"chbheq88l1z97","chunk_label":"unnamed-chunk-3"},{"row":90,"row_count":1,"visible":true,"expansion_state":0,"options":{"engine":"r","label":"unnamed-chunk-314"},"document_id":"7980DB40","chunk_id":"c02ju0n6dimgq","chunk_label":"unnamed-chunk-4"},{"row":124,"row_count":1,"visible":true,"expansion_state":0,"options":{"engine":"r","label":"unnamed-chunk-338"},"document_id":"7980DB40","chunk_id":"cyj1149l1np5y","chunk_label":"unnamed-chunk-5"},{"row":156,"row_count":1,"visible":true,"expansion_state":0,"options":{"engine":"r","label":"unnamed-chunk-339"},"document_id":"7980DB40","chunk_id":"covv73hzbg4cd","chunk_label":"unnamed-chunk-6"},{"row":175,"row_count":1,"visible":true,"expansion_state":0,"options":{"engine":"r","label":"unnamed-chunk-341"},"document_id":"7980DB40","chunk_id":"cz3tvtvzkzigw","chunk_label":"unnamed-chunk-7"}],"doc_write_time":1620482672,"chunk_rendered_width":605}